README.rst
setup.py
sops/__init__.py
sops.egg-info/PKG-INFO
sops.egg-info/SOURCES.txt
sops.egg-info/dependency_links.txt
sops.egg-info/entry_points.txt
sops.egg-info/requires.txt
sops.egg-info/top_level.txt
sops.egg-info/zip-safe
tests/__init__.py
tests/test_sops.py