Metadata-Version: 1.1
Name: sops
Version: 1.17
Summary: Secrets OPerationS (sops) is an editor of encrypted files
Home-page: https://github.com/mozilla/sops
Author: Julien Vehent
Author-email: jvehent@mozilla.com
License: MPL
Keywords: mozilla secret credential encryption aws kms
Platform: UNKNOWN
Classifier: Development Status :: 5 - Production/Stable
Classifier: Topic :: Software Development :: Libraries :: Python Modules
Classifier: License :: OSI Approved :: Mozilla Public License 2.0 (MPL 2.0)
